si4ti/_si4ti_python.cpython-310-darwin.so
si4ti/__init__.py
si4ti/.dylibs/libomp.dylib
si4ti-1.1.0.dist-info/RECORD
si4ti-1.1.0.dist-info/LICENSE
si4ti-1.1.0.dist-info/WHEEL
si4ti-1.1.0.dist-info/METADATA
