Metadata-Version: 2.1
Name: si4ti
Version: 1.1.0
Summary: si4ti is a LGPL licensed seismic inversion tool for monitoring effects in 4D seismic from changes in acoustic properties of a reservoir.
Author: Equinor ASA
Maintainer: Equinor ASA
License:                   GNU LESSER GENERAL PUBLIC LICENSE
Classifier: Development Status :: 3 - Alpha
Classifier: Intended Audience :: Science/Research
Classifier: Natural Language :: English
Classifier: Operating System :: MacOS :: MacOS X
Classifier: Operating System :: POSIX :: Linux
Classifier: Programming Language :: C++
Classifier: Programming Language :: Python :: 3 :: Only
Classifier: Programming Language :: Python :: 3.10
Classifier: Programming Language :: Python :: 3.11
Classifier: Programming Language :: Python :: 3.12
Classifier: Programming Language :: Python :: 3.13
Classifier: Topic :: Scientific/Engineering :: Physics
Project-URL: Homepage, https://github.com/equinor/si4ti
Project-URL: Bug Tracker, https://github.com/equinor/si4ti/issues
Requires-Python: >=3.10
Requires-Dist: numpy>=1.20
Requires-Dist: xtgeo
Provides-Extra: test
Requires-Dist: pytest; extra == "test"
Requires-Dist: pytest-memray; extra == "test"
